[{
  "id": "amorisdiuinieth00snyd",
  "ark_id": "ark:/13960/t77s8v97m",
  "spineXML": "http://emblemimages.library.illinois.edu/amorisdiuinieth00snyd/supplementary/amorisdiuinieth00snyd_mods.xml",
  "has_emblems": false,
  "search_keywords": "Amoris diuini et humani effectus varii Sacræ Scripturæ Sanctorumq; PP. sententijs : ac Gallicis versibus illustrati Snyders, Michael. Schoor, Gillis van b. 1596 Mallery, Karel van 1571-ca. 1635 text be Antuerpiæ Apud Michaelem Snyders 1626 monographic lat fre reformatted digital print [57] leaves of plates ; 15 cm. Engraved throughout. Majority of plates signed by M. Snyders; many also signed G. van Schoor; one has monogram of C. de Mallery. Without signatures, pagination, or foliation. Emblems https://archive.org/details/amorisdiuinieth00snyd https://archive.org/details/amorisdiuinieth00snyd emblem books aacr2 NDD 841022 20121209230042.0 000609705 Converted from MARCXML to MODS version 3.3 using MARC21slim2MODS3-3.xsl (Revision 1.54) ark:/13960/t77s8v97m http://hdl.handle.net/2027/dul1.ark:/13960/t77s8v97m",
  "search_title": [
"Amoris diuini et humani effectus varii Sacræ Scripturæ Sanctorumq; PP. sententijs : ac Gallicis versibus illustrati"
],
  "search_publication_date": "1626",
  "search_publication_place": "Antuerpiæ",
  "search_publisher": "Apud Michaelem Snyders",
  "search_name": [
"Snyders, Michael.",
"Schoor, Gillis van b. 1596",
"Mallery, Karel van 1571-ca. 1635"
],
  "display_title": "Amoris diuini et humani effectus: varii Sacræ Scripturæ Sanctorumq; PP. sententijs : ac Gallicis versibus illustrati",
  "display_name": [
"Snyders, Michael.",
"Schoor, Gillis van b. 1596",
"Mallery, Karel van 1571-ca. 1635"
],
  "display_publication_date": "1626",
  "display_publication_place": "Antuerpiæ",
  "display_collection": "Duke University",
  "display_first_pictura_link": null,
  "facet_collection_code": "Duke",
  "facet_language_code": [
"lat",
"fre"
],
  "facet_publication_century": "17th century",
  "facet_publication_place": "Antuerpiæ"
}]