[{
  "id": "63649778X",
  "ark_id": null,
  "spineXML": "http://emblemimages.library.illinois.edu/63649778X/supplementary/63649778X_spine.xml",
  "has_emblems": true,
  "search_keywords": "Monumentum Extremi Honoris, Perennis Virtutis Piis Manibus Serenissimi, Ac Potentissimi Principis Ferdinandi Mariae, Utriusque Bavariae, ac Superioris Palatinatus Ducis, Comitis Palatini Rheni, S.R.I. Archidapiferi Electoris, Landgravii Leuchtenbergensis In Regio Electorali Templo RR. PP. Clericorum Regularium Erectum, ac Nuncupatum urn:nbn:de:gbv:23-drucke/xb-4f-364-1s0 iai- amu- i-o- begu 3 1679R 12:127498N http://diglib.hab.de/drucke/xb-4f-364-1s/start.htm 1679 Monachii Jaecklinus 2010 HAB Wolfenbüttel [Electronic ed.] Gaetano Felice Verani Verani, Gaetano Felice aut Bayern, Kurfürst Ferdinand Maria <Bayern, Kurfürst> oth Utriusque Bavariae ac Superioris Palatinatus Dux Comes Palatinus Rheni Sacri Romani Imperii Archidapifer & Elector Maximilianus Emmanuel Maximilianus Emmanuel, Utriusque Bavariae ac Superioris Palatinatus Dux Comes Palatinus Rheni Sacri Romani Imperii Archidapifer & Elector dte C. A. clb Michael Wening Wening, Michael clb Johann Jäcklin Jäcklin, Johann prt lat Emblematica Online Verani, Gaetano Felice: Monumentum Extremi Honoris, Perennis Virtutis Piis Manibus Serenissimi, Ac Potentissimi Principis Ferdinandi Mariae, Utriusque Bavariae, ac Superioris Palatinatus Ducis, Comitis Palatini Rheni, S.R.I. Archidapiferi Electoris, Landgravii Leuchtenbergensis GBV 53619050X Leichenpredigt Ordensliteratur:Theatiner Emblembuch [3] Bl., 179 S 2° zahlr. Ill. (Kupferst.) 63649778X Converted from PICA using a local XSL transformation script DE-23",
  "search_title": [
"Monumentum Extremi Honoris, Perennis Virtutis Piis Manibus Serenissimi, Ac Potentissimi Principis Ferdinandi Mariae, Utriusque Bavariae, ac Superioris Palatinatus Ducis, Comitis Palatini Rheni, S.R.I. Archidapiferi Electoris, Landgravii Leuchtenbergensis In Regio Electorali Templo RR. PP. Clericorum Regularium Erectum, ac Nuncupatum"
],
  "search_publication_date": "1679",
  "search_publication_place": "Monachii",
  "search_publisher": "Jaecklinus",
  "search_name": [
"Verani, Gaetano Felice",
"Ferdinand Maria <Bayern, Kurfürst>",
"Maximilianus Emmanuel, Utriusque Bavariae ac Superioris Palatinatus Dux Comes Palatinus Rheni Sacri Romani Imperii Archidapifer & Elector",
"C. A.",
"Wening, Michael",
"Jäcklin, Johann"
],
  "display_title": "Monumentum Extremi Honoris, Perennis Virtutis Piis Manibus Serenissimi, Ac Potentissimi Principis Ferdinandi Mariae, Utriusque Bavariae, ac Superioris Palatinatus Ducis, Comitis Palatini Rheni, S.R.I. Archidapiferi Electoris, Landgravii Leuchtenbergensis: In Regio Electorali Templo RR. PP. Clericorum Regularium Erectum, ac Nuncupatum",
  "display_name": [
"Verani, Gaetano Felice",
"Ferdinand Maria <Bayern, Kurfürst>",
"Maximilianus Emmanuel, Utriusque Bavariae ac Superioris Palatinatus Dux Comes Palatinus Rheni Sacri Romani Imperii Archidapifer & Elector",
"C. A.",
"Wening, Michael",
"Jäcklin, Johann"
],
  "display_publication_date": "1679",
  "display_publication_place": "Monachii",
  "display_collection": "Herzog August Bibliothek",
  "display_first_pictura_link": "http://emblemimages.library.illinois.edu/63649778X/_access/pictura/E001943.jpg",
  "facet_collection_code": "HAB",
  "facet_language_code": [
"lat"
],
  "facet_publication_century": "17th century",
  "facet_publication_place": "Monachii"
}]