[{
  "id": "depaceinterhispa00molu",
  "ark_id": "ark:/13960/t8gf1597p",
  "spineXML": "http://emblemimages.library.illinois.edu/depaceinterhispa00molu/supplementary/depaceinterhispa00molu_spine.xml",
  "has_emblems": true,
  "search_keywords": "De pace inter hispaniarum et galliarum reges habita panegyrica dictio De pace inter hispaniarvm et galliarvm reges habita Molus, Antonius Maria. creator text Engravings-Italy-17th century. Occasional poems-Italy-17th century. Emblem books-Italy-17th century. it Mediolani Ex typographia Antonij Malatestae ... 1660 monographic ita reformatted digital print 24 p., [1] folded leaf : ill. ; 23 cm. (4to) P. Antonius Maria Molus. Signatures: A¹². Illustrations include three copperplate engravings signed Bianc. The folded leaf is a figural poem, spelling out the word pax in a circle. e-fr--- e-sp--- e-it--- France. 1659 Nov. 7. Emblems https://archive.org/details/depaceinterhispa00molu https://archive.org/details/depaceinterhispa00molu emblem books aacr2 dcrb CMalG 021125 20080521181453.0 596027 Converted from MARCXML to MODS version 3.3 using MARC21slim2MODS3-3.xsl (Revision 1.54) ark:/13960/t8gf1597p http://hdl.handle.net/2027/gri.ark:/13960/t8gf1597p",
  "search_title": [
"De pace inter hispaniarum et galliarum reges habita panegyrica dictio",
"De pace inter hispaniarvm et galliarvm reges habita"
],
  "search_publication_date": "1660",
  "search_publication_place": "Mediolani",
  "search_publisher": "Ex typographia Antonij Malatestae ...",
  "search_name": [
"Molus, Antonius Maria."
],
  "display_title": "De pace inter hispaniarum et galliarum reges habita: panegyrica dictio",
  "display_name": [
"Molus, Antonius Maria."
],
  "display_publication_date": "1660",
  "display_publication_place": "Mediolani",
  "display_collection": "Getty Library",
  "display_first_pictura_link": "http://emblemimages.library.illinois.edu/depaceinterhispa00molu/_access/pictura/E024409.jpg",
  "facet_collection_code": "Getty",
  "facet_language_code": [
"ita"
],
  "facet_publication_century": "17th century",
  "facet_publication_place": "Mediolani"
}]