[{
  "id": "meditationesembl00voge",
  "ark_id": "ark:/13960/t4bp0kr75",
  "spineXML": "http://emblemimages.library.illinois.edu/meditationesembl00voge/supplementary/meditationesembl00voge_spine.xml",
  "has_emblems": true,
  "search_keywords": "Meditationes emblematicae de restaurata pace Germaniae = Sinnebilder von dem widergebrachten Teutschen Frieden Sinnebilder von dem widergebrachten Teutschen Frieden Meditationes de restaurata pace Sinnbilder von dem wiedergebrachten Frieden in Teutschlandt Vogel, Johann 1589-1663 Zunner, Johann David active approximately 1653-1705 printer. Zunner, Johann David, active approximately 1653-1705 text Emblem books-Germany-17th century. gw Francofurti Apud Joh. Dav. Zunnerum [1649] 1649 monographic lat ger print [5], XXIV, XXIV, [3] p. : ill. (engravings) ; 22 cm (4to) Publication date appears as chronogram on title-page. Place of publication and printer from additional engraved title-page: Meditationes de restaurata pace = Sinnbilder von dem wiedergebrachten Frieden in Teutschlandt / Johannis Vogelij, with imprint: Francofurti : Apud Joh. Dav. Zunnerum. Signatures: A-G. 1649 inscribed in ink on title-page. Emblems Early works to 1800 Emblem books, Latin Germany 17th century Emblem books, German Germany 17th century https://hdl.handle.net/2027/uiuo.ark:/13960/t4bp0kr75",
  "search_title": [
"Meditationes emblematicae de restaurata pace Germaniae = Sinnebilder von dem widergebrachten Teutschen Frieden",
"Sinnebilder von dem widergebrachten Teutschen Frieden",
"Meditationes de restaurata pace",
"Sinnbilder von dem wiedergebrachten Frieden in Teutschlandt"
],
  "search_publication_date": "1649",
  "search_publication_place": "Francofurti",
  "search_publisher": "Apud Joh. Dav. Zunnerum",
  "search_name": [
"Vogel, Johann 1589-1663",
"Zunner, Johann David, active approximately 1653-1705"
],
  "display_title": "Meditationes emblematicae de restaurata pace Germaniae =: Sinnebilder von dem widergebrachten Teutschen Frieden",
  "display_name": [
"Vogel, Johann 1589-1663",
"Zunner, Johann David, active approximately 1653-1705"
],
  "display_publication_date": "1649",
  "display_publication_place": "Francofurti",
  "display_collection": "University of Illinois at UC",
  "display_first_pictura_link": "http://emblemimages.library.illinois.edu/meditationesembl00voge/_access/pictura/E000001.jpg",
  "facet_collection_code": "Illinois",
  "facet_language_code": [
"lat",
"ger"
],
  "facet_publication_century": "17th century",
  "facet_publication_place": "Francofurti"
}]