[{
  "id": "leimaginideidegl01cart",
  "ark_id": "ark:/13960/t7gq87s9w",
  "spineXML": "http://emblemimages.library.illinois.edu/leimaginideidegl01cart/supplementary/leimaginideidegl01cart_mods.xml",
  "has_emblems": false,
  "search_keywords": "Le imagini dei degli antichi Cartari, Vincenzo b. ca. 1500 creator Cartari, Vincenzo, b. ca. 1500 Malfatti, Cesare b. ca. 1550 Malfatti, Cesare, b. ca. 1550 text it In Padoa appresso Pietro Paulo Tozzi libraro 1608 monographic ita reformatted digital print [40], 512, [7] p. illus. 20 cm. del Signor Vincenzo Cartari Regiano, novamente ristampate & ricorette ... con l'agiunta di molte principali imagini che nell'altre mancavano, e con la espositione in epilogo di ciasceduna & suo significato ... per Cesare Malfatti Padoano, con un cathalogo del medesimo de 100. è piu famosi dei ... Opera utilissima à historici, poeti, pittori, scultori, & professori di belle lettere. Engraved title page. 138 nearly full-page engravings. Colophon: In Padova, nella stamparia de Lorenzo Pasquati. 1607. Ad instantia di Pietro Paolo Tozzi, libraro in Padova, all'insegna del Giesù. Mythology, Classical Early works to 1800 https://archive.org/details/leimaginideidegl01cart https://archive.org/details/leimaginideidegl01cart emblem books AZU 760323 20130121142938.0 002432627 Converted from MARCXML to MODS version 3.3 using MARC21slim2MODS3-3.xsl (Revision 1.54) ark:/13960/t7gq87s9w http://hdl.handle.net/2027/dul1.ark:/13960/t7gq87s9w",
  "search_title": [
"Le imagini dei degli antichi"
],
  "search_publication_date": "1608",
  "search_publication_place": "In Padoa",
  "search_publisher": "appresso Pietro Paulo Tozzi libraro",
  "search_name": [
"Cartari, Vincenzo, b. ca. 1500",
"Malfatti, Cesare, b. ca. 1550"
],
  "display_title": "imagini dei degli antichi",
  "display_name": [
"Cartari, Vincenzo, b. ca. 1500",
"Malfatti, Cesare, b. ca. 1550"
],
  "display_publication_date": "1608",
  "display_publication_place": "In Padoa",
  "display_collection": "Duke University",
  "display_first_pictura_link": null,
  "facet_collection_code": "Duke",
  "facet_language_code": [
"ita"
],
  "facet_publication_century": "17th century",
  "facet_publication_place": "In Padoa"
}]